reorder/__init__.py
reorder/cli.py
reorder/image.py
reorder/interface.py
reorder/py.typed
image_reorder-0.5.0.dist-info/METADATA
image_reorder-0.5.0.dist-info/WHEEL
image_reorder-0.5.0.dist-info/entry_points.txt
image_reorder-0.5.0.dist-info/licenses/LICENSE
image_reorder-0.5.0.dist-info/licenses/NOTICE
image_reorder-0.5.0.dist-info/RECORD
