Metadata-Version: 2.4
Name: image-reorder
Version: 0.5.0
Summary: Reorder images from multiple cameras into a single folder
Project-URL: Homepage, https://pypi.org/project/image-reorder/
Project-URL: Repository, https://github.com/pronovic/image-reorder
Project-URL: Changelog, https://github.com/pronovic/image-reorder/releases
Project-URL: Issues, https://github.com/pronovic/image-reorder/issues
Author-email: "Kenneth J. Pronovici" <pronovic@ieee.org>
License-Expression: Apache-2.0
License-File: LICENSE
License-File: NOTICE
Classifier: Environment :: Console
Classifier: Intended Audience :: Developers
Classifier: Natural Language :: English
Classifier: Operating System :: Unix
Classifier: Programming Language :: Python :: 3
Classifier: Programming Language :: Python :: 3.11
Classifier: Programming Language :: Python :: 3.12
Classifier: Programming Language :: Python :: 3.13
Classifier: Programming Language :: Python :: 3.14
Classifier: Topic :: Multimedia :: Graphics
Requires-Python: <4,>=3.11
Requires-Dist: attrs>=24.2.0
Requires-Dist: click<9.0.0,>=8.1.7
Requires-Dist: pillow<12.0.0,>=11.0.0
